auto_upgrade_pip/__init__.py
auto_upgrade_pip/__main__.py
auto_upgrade_pip-0.2.1.data/data/Scripts/pip-upgrade.exe
auto_upgrade_pip-0.2.1.dist-info/licenses/LICENSE
auto_upgrade_pip-0.2.1.dist-info/METADATA
auto_upgrade_pip-0.2.1.dist-info/WHEEL
auto_upgrade_pip-0.2.1.dist-info/top_level.txt
auto_upgrade_pip-0.2.1.dist-info/RECORD
